kazecore/BigInteger.py
kazecore/Fixed8.py
kazecore/KeyPair.py
kazecore/UInt160.py
kazecore/UInt256.py
kazecore/UIntBase.py
kazecore/__init__.py
kazecore/Cryptography/Crypto.py
kazecore/Cryptography/ECCurve.py
kazecore/Cryptography/Helper.py
kazecore/Cryptography/MerkleTree.py
kazecore/Cryptography/__init__.py
kazecore/IO/BinaryReader.py
kazecore/IO/BinaryWriter.py
kazecore/IO/Mixins.py
kazecore/IO/__init__.py
kazecore/bin/__init__.py
kazecore/bin/cli.py
kazecore-0.6.8.dist-info/LICENSE
kazecore-0.6.8.dist-info/METADATA
kazecore-0.6.8.dist-info/WHEEL
kazecore-0.6.8.dist-info/entry_points.txt
kazecore-0.6.8.dist-info/top_level.txt
kazecore-0.6.8.dist-info/RECORD
