Metadata-Version: 2.1
Name: kazecore
Version: 0.6.8
Summary: Core functionality of kaze-python
Home-page: https://github.com/KAZEBLOCKCHAIN/kaze-python-core
Author: Kaze Blockchain
Author-email: development@Kazesolutions.ch
License: MIT license
Keywords: kazecore,kaze,python,node
Platform: UNKNOWN
Classifier: Development Status :: 3 - Alpha
Classifier: Intended Audience :: Developers
Classifier: License :: OSI Approved :: MIT License
Classifier: Natural Language :: English
Classifier: Programming Language :: Python :: 3
Classifier: Programming Language :: Python :: 3.5
Classifier: Programming Language :: Python :: 3.6
Requires-Python: >=3.4
Requires-Dist: base58 (==1.0.2)
Requires-Dist: bitcoin (==1.1.42)
Requires-Dist: ecdsa (==0.13)
Requires-Dist: logzero (==1.5.0)
Requires-Dist: mpmath (==1.0.0)
Requires-Dist: pycryptodome (==3.6.6)
Requires-Dist: scrypt (==0.8.6)
